autosec/__init__.py
autosec/autocred.py
autosec/autolog.py
autosec/cli.py
autosec-2.1.2.dist-info/licenses/LICENSE
autosec-2.1.2.dist-info/METADATA
autosec-2.1.2.dist-info/WHEEL
autosec-2.1.2.dist-info/entry_points.txt
autosec-2.1.2.dist-info/top_level.txt
autosec-2.1.2.dist-info/RECORD
