Metadata-Version: 2.4
Name: autosec
Version: 2.1.2
Summary: A collection of utilities for security operations and automation.
Author-email: Dylan Diamond <dylandiamond1997@outlook.com>
Requires-Python: >=3.11
License-File: LICENSE
Requires-Dist: cryptography
Requires-Dist: python-dotenv
Requires-Dist: requests
Dynamic: license-file
